automated_machineLearning_methods/__init__.py
automated_machineLearning_methods/automated_machineLearning_methods.py
tests/__init__.py
tests/test_operations.py
automated_machineLearning_methods-0.1.0.dist-info/LICENSE.txt
automated_machineLearning_methods-0.1.0.dist-info/METADATA
automated_machineLearning_methods-0.1.0.dist-info/WHEEL
automated_machineLearning_methods-0.1.0.dist-info/top_level.txt
automated_machineLearning_methods-0.1.0.dist-info/RECORD
